__init__.py
WeChatEnterprise/__init__.py
WeChatEnterprise/API/SendMsg.py
WeChatEnterprise/API/__init__.py
WeChatEnterprise_hahaleyile-0.0.6.dist-info/LICENSE
WeChatEnterprise_hahaleyile-0.0.6.dist-info/METADATA
WeChatEnterprise_hahaleyile-0.0.6.dist-info/WHEEL
WeChatEnterprise_hahaleyile-0.0.6.dist-info/top_level.txt
WeChatEnterprise_hahaleyile-0.0.6.dist-info/RECORD
