Metadata-Version: 2.1
Name: WeChatEnterprise-hahaleyile
Version: 0.0.6
Summary: WeChatEnterpriseApi
Author: Kevin Zhu
Author-email: hahaleyile@126.com
Maintainer-email: Kevin Zhu <hahaleyile@126.com>
Project-URL: repository, https://github.com/hahaleyile/WeChatEnterprise
Classifier: License :: OSI Approved :: MIT License
Classifier: Programming Language :: Python :: 3
Requires-Python: >=3.6
License-File: LICENSE
Requires-Dist: redis
Requires-Dist: requests
